detectStoma
