Metadata-Version: 1.1
Name: detectStoma
Version: 0.0.13
Summary: API for stoma detection
Home-page: https://github.com/ancasag/detectStoma
Author: Ángela Casado
Author-email: angela.casado@unirioja.es
License: UNKNOWN
Keywords: stoma,detection,model.weights,model.cfg,model.name,model.data
Platform: UNKNOWN
Classifier: Development Status :: 4 - Beta
Classifier: Intended Audience :: Developers
Classifier: Topic :: Software Development :: Build Tools
Classifier: License :: OSI Approved :: MIT License
Classifier: Programming Language :: Python :: 3.6
